{
  "name": "Mohamed Nishath M",
  "age": "23",
  "email": "nishathmohamed01@gmail.com",
  "portfolio": "https://my-portfolio-lovat-alpha.vercel.app/",
  "about": "I am a dedicated MERN stack developer with 15 months of hands-on experience. My experience spans in a product-based project, including developing authentication frameworks. I am passionate about continuous learning and eager to contribute to innovative and impactful projects .",
  "phone": "6380844458",
  "github": "https://github.com/nich-nichy",
  "linkedIn": "https://www.linkedin.com/in/mohamed-nishath-m-049516191/",
  "skills": [
    "HTML",
    "CSS",
    "Javascript",
    "Python",
    "React Js",
    "Express Js",
    "Node Js",
    "Power BI"
  ],
  "education": [
    {
      "name": "Nilgiris matriculation higher secondary school",
      "location": "Lovedale, Ooty",
      "till": 2018,
      "percentage": "72.2",
      "studied": "HSC"
    },
    {
      "name": "P. A college of engineering & technology",
      "location": "Pollachi, Coimbatore",
      "till": 2020,
      "percentage": "85.1",
       "studied": "Diploma in ECE"
    },
    {
      "name": "Mahalingam college of engineering & technology",
      "location": "Pollachi, Coimbatore",
      "till": 2023,
      "percentage": "83.3",
       "studied": "B.Tech in Information Technology"
    }
  ],
  "companies": [
    {
      "designationOne": {
        "name": "Aroopa",
        "position": "Intern",
        "from": "Mar-2023",
        "to": "Sep-2023"
      },
      "designationTwo": {
        "name": "Aroopa",
        "position": "Trainee software developer",
        "from": "Aug-2023",
        "to": "May-2024"
      }
    }
  ],
  "Certification": [
    {
      "name": "Zen Class Full Stack Development Bootcamp(MERN)",
      "issuedFrom": "Guvi",
      "about": "MERN development"
    },
    {
      "name": "The complete 2021 web development bootcamp",
      "issuedFrom": "Udemy",
      "about": "Full Stack Development"
    }
  ]
}
